auditicy/__init__.py
auditicy/django_integration/__init__.py
auditicy/fastapi_integration/__init__.py
auditicy/flask_integration/__init__.py
auditicy-0.0.1a2.dist-info/licenses/LICENSE
auditicy-0.0.1a2.dist-info/METADATA
auditicy-0.0.1a2.dist-info/WHEEL
auditicy-0.0.1a2.dist-info/top_level.txt
auditicy-0.0.1a2.dist-info/RECORD
