Metadata-Version: 2.4
Name: auditicy
Version: 0.0.1a2
Summary: Flexible audit logging for Django, Flask, and FastAPI.
Author-email: Joan Camps Morey <joan.camps@zeent.com>
License-Expression: MIT
Project-URL: Homepage, https://github.com/zeent/auditicy
Project-URL: Repository, https://github.com/zeent/auditicy
Project-URL: Issues, https://github.com/zeent/auditicy/issues
Classifier: Development Status :: 3 - Alpha
Classifier: Intended Audience :: Developers
Classifier: Programming Language :: Python :: 3
Classifier: Framework :: Django
Classifier: Framework :: Flask
Classifier: Framework :: FastAPI
Classifier: Topic :: Software Development :: Libraries :: Application Frameworks
Requires-Python: >=3.7
License-File: LICENSE
Dynamic: license-file
